CCF251-Introducao-aos-Sistemas-Logicos-e-Digitais/Urna TP2/urnaeletronica.v
module urnaeletronica(control,digit,tisabella,tclaudio,tfilipe,tguilherme,tnulo,clock,valid,finish,votestatus);
	input wire clock,valid,finish;
	input wire [3:0]digit;
	input wire [2:0]control;
	output reg [7:0]tisabella = 8'b00000000;
	output reg [7:0]tclaudio = 8'b00000000;
	output reg [7:0]tfilipe = 8'b00000000;
	output reg [7:0]tguilherme = 8'b00000000;
	output reg [7:0]tnulo = 8'b00000000;
	output reg votestatus;
	reg [3:0]estado = 4'b0000;
	reg [7:0]isabella = 8'b00000000;
	reg [7:0]claudio = 8'b00000000;
	reg [7:0]filipe = 8'b00000000;
	reg [7:0]guilherme = 8'b00000000;
	reg [7:0]nulo = 8'b00000000;

		/* Isabella - 3474
		   Cláudio - 3492
		   Filipe - 3502
		   Guilherme - 3509
		*/

	always @(posedge clock) begin

	if(finish) begin
		case (control) //inicio case
			3'b000: begin //zera os resultados obtidos na eleicao
				isabella <= 8'b00000000;
				claudio <= 8'b00000000;
				filipe <= 8'b00000000;
				guilherme <= 8'b00000000;
				nulo <= 8'b00000000;
				tisabella <= 8'b00000000;
				tclaudio <= 8'b00000000;
				tfilipe <= 8'b00000000;
				tguilherme <= 8'b00000000;
				tnulo <= 8'b00000000;
			end
			3'b001: begin //atribui quantidade de votos finais para isabella
				tisabella <= isabella;
			end
			3'b010: begin //atribui quantidade de votos finais para claudio
				tclaudio <= claudio;
			end
			3'b011: begin //atribui quantidade de votos finais para filipe
				tfilipe <= filipe;
			end
			3'b100: begin //atribui quantidade de votos finais para guilherme
				tguilherme <= guilherme;
			end
			3'b101: begin //atribui quantidade de votos nulo
				tnulo <= nulo;
			end
		endcase //fim case
	end

		else if(~finish) begin
			case(estado) //inicio case

				4'b0000: begin //primeiro estado
					if((digit == 4'b0011) & (valid)) begin//comparando 3 em binário
						estado <= 4'b0001;
					end
					else begin //voto nulo
						estado <= 4'b0101; //vai para o segundo estado nulo
					end
				end
				//fim primeiro estado

				//inicio 2ºnumvoto
				4'b0001: begin //segundo estado
					if((digit == 4'b0100) & (valid)) begin //comparando 4 em binário
						estado <= 4'b0010;
					end
					else if((digit == 4'b0101) & (valid)) begin //comparando 5 em binário
						estado <= 4'b0010;
					end
					else begin //voto nulo
						estado <= 4'b0110; //vai para o terceiro estado nulo
					end
				end
				//fim segundo estado

				4'b0010: begin //terceiro estado
					if((digit == 4'b1001) & (valid)) begin //comparando 9 em binário
						estado <= 4'b1000;
					end
					else if((digit == 4'b0111) & (valid)) begin //comparando 7 em binário
						estado <= 4'b0011;
					end
					else if((digit == 4'b0000) & (valid)) begin //comparando 0 em binário
						estado <= 4'b0011;
					end
					else begin //voto nulo
						estado <= 4'b0100; //vai para o quarto estado nulo
					end
				end
				//fim terceiro estado


				4'b1000: begin //quarto estado
					if((digit == 4'b0010) & (valid)) begin //comparando 2 em binário
						claudio <= claudio + 8'b00000001; //contagem de votos para claudio
						votestatus <= 1;
						estado <= 4'b0000;
					end
					else begin //voto nulo
						nulo <= nulo + 8'b00000001; //contagem de votos nulos
						votestatus <= 0;
						estado <= 4'b0000;
					end
				end
				//fim quarto estado

				4'b0011: begin //quarto estado
					if((digit == 4'b1001) & (valid)) begin //comparando 9 em binário
						guilherme <= guilherme + 8'b00000001; //contagem de votos para guilherme
						votestatus <= 1;
						estado <= 4'b0000;
					end
					else if((digit == 4'b0100) & (valid)) begin //comparando 4 em binário
						isabella <= isabella + 8'b00000001; //contagem de votos para isabella
						votestatus <= 1;
						estado <= 4'b0000;
					end
					else if((digit == 4'b0010) & (valid)) begin //comparando 2 em binário
						filipe <= filipe + 8'b00000001; //contagem de votos para filipe
						votestatus <= 1;
						estado <= 4'b0000;
					end
					else begin //voto nulo
						nulo <= nulo + 8'b00000001; //contagem de votos nulos
						votestatus <= 0;
						estado <= 4'b0000;
					end
				end
				//fim quarto estado

				//segundo estado nulo
				4'b0101: begin
					if(valid) begin
						estado <= 4'b0110;
					end
				end
				// fim segundo estado nulo

				//terceiro estado nulo
				4'b0110: begin
					if(valid) begin
						estado <= 4'b0100;
					end
				end
				//fim terceiro estado nulo

				//quarto estado nulo
				4'b0100: begin
					if(valid) begin
						nulo <= nulo + 8'b00000001; //contagem de votos nulos
						votestatus <= 0;
						estado <= 4'b0000;
					end
				//fim quarto estado nulo

				end
			endcase //fim case
		end

	end
endmodule

CCF251-Introducao-aos-Sistemas-Logicos-e-Digitais/Urna TP2/testbench.v
`include "urnaeletronica.v"
module testbench();
reg clock,valid,finish;
reg [3:0]digit;
reg [2:0]control;
wire [7:0]tisabella;
wire [7:0]tclaudio;
wire [7:0]tfilipe;
wire [7:0]tguilherme;
wire [7:0]tnulo;
wire votestatus;

urnaeletronica instancial(.votestatus(votestatus), .control(control), .clock(clock), .valid(valid), .finish(finish), .digit(digit), .tisabella(tisabella), .tclaudio(tclaudio), .tfilipe(tfilipe), .tguilherme(tguilherme), .tnulo(tnulo));

initial begin
  $dumpfile("urnaeletronica.vcd");
  $dumpvars(0, testbench);
  $display("-----Urna Eletronica-----");
  $monitor("- Votos para Isabella: %d\n- Votos para Claudio: %d\n- Votos para Filipe: %d\n- Votos para Guilherme: %d\n- Votos nulos:%d\n", tisabella, tclaudio, tfilipe, tguilherme, tnulo);
end

initial begin

// Inserindo dígitos para Isabella
  #1; clock = 0;
  #1; clock = 1; finish = 0; valid = 0;digit = 4'b0011; valid = 1;
  #1; clock = 0;
  #1; clock = 1; valid = 0; digit = 4'b0100; valid = 1;
  #1; clock = 0;
  #1; clock = 1; valid = 0; digit = 4'b0111; valid = 1;
  #1; clock = 0;
  #1; clock = 1; valid = 0; digit = 4'b0100; valid = 1;

  // Inserindo dígitos para Cláudio
  #1; clock = 0;
  #1; clock = 1; valid = 0; digit = 4'b0011; valid = 1;
  #1; clock = 0;
  #1; clock = 1; valid = 0; digit = 4'b0100; valid = 1;
  #1; clock = 0;
  #1; clock = 1; valid = 0; digit = 4'b1001; valid = 1;
  #1; clock = 0;
  #1; clock = 1; valid = 0; digit = 4'b0010; valid = 1;

// Inserindo dígitos para Filipe
  #1; clock = 0;
  #1; clock = 1; valid = 0; digit = 4'b0011; valid = 1;
  #1; clock = 0;
  #1; clock = 1; valid = 0; digit = 4'b0101; valid = 1;
  #1; clock = 0;
  #1; clock = 1; valid = 0; digit = 4'b0000; valid = 1;
  #1; clock = 0;
  #1; clock = 1; valid = 0; digit = 4'b0010; valid = 1;

// Inserindo dígitos para Guilherme
  #1; clock = 0;
  #1; clock = 1; valid = 0; digit = 4'b0011; valid = 1;
  #1; clock = 0;
  #1; clock = 1; valid = 0; digit = 4'b0101; valid = 1;
  #1; clock = 0;
  #1; clock = 1; valid = 0; digit = 4'b0000; valid = 1;
  #1; clock = 0;
  #1; clock = 1; valid = 0; digit = 4'b1001; valid = 1;

// Inserindo dígitos para Nulo
  #1; clock = 0;
  #1; clock = 1; valid = 0; digit = 4'b0011; valid = 1;
  #1; clock = 0;
  #1; clock = 1; valid = 0; digit = 4'b0101; valid = 1;
  #1; clock = 0;
  #1; clock = 1; valid = 0; digit = 4'b0000; valid = 1;
  #1; clock = 0;
  #1; clock = 1; valid = 0; digit = 4'b1111; valid = 1;


  #1; clock = 0;
  #1; clock = 1; finish = 1; clock = 0;//Finalizando a votação
  #1; clock = 1 ;control = 3'b001; //mostrando votos de Isabella
  #1; clock = 0;
  #1; clock = 1; control = 3'b010; //mostrando votos de Cláudio
  #1; clock = 0;
  #1; clock = 1; control = 3'b011; //mostrando votos de Filipe
  #1; clock = 0;
  #1; clock = 1; control = 3'b100; //mostrando votos de Guilherme
  #1; clock = 0;
  #1; clock = 1; control = 3'b101; //mostrando votos nulos
  #1; clock = 0;
  #1; clock = 1; control = 3'b000; //zerando os votos
  #1;
  $finish;
end

endmodule

CCF251-Introducao-aos-Sistemas-Logicos-e-Digitais/Urna TP2/urnaeletronica.vcd
$date
	Sat Dec  1 14:13:32 2018
$end
$version
	Icarus Verilog
$end
$timescale
	1s
$end
$scope module testbench $end
$var wire 1 ! votestatus $end
$var wire 8 " tnulo [7:0] $end
$var wire 8 # tisabella [7:0] $end
$var wire 8 $ tguilherme [7:0] $end
$var wire 8 % tfilipe [7:0] $end
$var wire 8 & tclaudio [7:0] $end
$var reg 1 ' clock $end
$var reg 3 ( control [2:0] $end
$var reg 4 ) digit [3:0] $end
$var reg 1 * finish $end
$var reg 1 + valid $end
$scope module instancial $end
$var wire 1 ' clock $end
$var wire 3 , control [2:0] $end
$var wire 4 - digit [3:0] $end
$var wire 1 * finish $end
$var wire 1 + valid $end
$var reg 8 . claudio [7:0] $end
$var reg 4 / estado [3:0] $end
$var reg 8 0 filipe [7:0] $end
$var reg 8 1 guilherme [7:0] $end
$var reg 8 2 isabella [7:0] $end
$var reg 8 3 nulo [7:0] $end
$var reg 8 4 tclaudio [7:0] $end
$var reg 8 5 tfilipe [7:0] $end
$var reg 8 6 tguilherme [7:0] $end
$var reg 8 7 tisabella [7:0] $end
$var reg 8 8 tnulo [7:0] $end
$var reg 1 ! votestatus $end
$upscope $end
$upscope $end
$enddefinitions $end
#0
$dumpvars
b0 8
b0 7
b0 6
b0 5
b0 4
b0 3
b0 2
b0 1
b0 0
b0 /
b0 .
bx -
bx ,
x+
x*
bx )
bx (
x'
b0 &
b0 %
b0 $
b0 #
b0 "
x!
$end
#1
0'
#2
b1 /
b11 )
b11 -
1+
0*
1'
#3
0'
#4
b10 /
b100 )
b100 -
1+
1'
#5
0'
#6
b11 /
b111 )
b111 -
1+
1'
#7
0'
#8
b0 /
1!
b1 2
b100 )
b100 -
1+
1'
#9
0'
#10
b1 /
b11 )
b11 -
1+
1'
#11
0'
#12
b10 /
b100 )
b100 -
1+
1'
#13
0'
#14
b1000 /
b1001 )
b1001 -
1+
1'
#15
0'
#16
b0 /
b1 .
b10 )
b10 -
1+
1'
#17
0'
#18
b1 /
b11 )
b11 -
1+
1'
#19
0'
#20
b10 /
b101 )
b101 -
1+
1'
#21
0'
#22
b11 /
b0 )
b0 -
1+
1'
#23
0'
#24
b0 /
b1 0
b10 )
b10 -
1+
1'
#25
0'
#26
b1 /
b11 )
b11 -
1+
1'
#27
0'
#28
b10 /
b101 )
b101 -
1+
1'
#29
0'
#30
b11 /
b0 )
b0 -
1+
1'
#31
0'
#32
b0 /
b1 1
b1001 )
b1001 -
1+
1'
#33
0'
#34
b1 /
b11 )
b11 -
1+
1'
#35
0'
#36
b10 /
b101 )
b101 -
1+
1'
#37
0'
#38
b11 /
b0 )
b0 -
1+
1'
#39
0'
#40
b0 /
0!
b1 3
b1111 )
b1111 -
1+
1'
#41
0'
#42
1*
0'
#43
b1 #
b1 7
b1 (
b1 ,
1'
#44
0'
#45
b1 &
b1 4
b10 (
b10 ,
1'
#46
0'
#47
b1 %
b1 5
b11 (
b11 ,
1'
#48
0'
#49
b1 $
b1 6
b100 (
b100 ,
1'
#50
0'
#51
b1 "
b1 8
b101 (
b101 ,
1'
#52
0'
#53
b0 "
b0 8
b0 $
b0 6
b0 %
b0 5
b0 &
b0 4
b0 #
b0 7
b0 3
b0 1
b0 0
b0 .
b0 2
b0 (
b0 ,
1'
